sublime_music/__init__.py
sublime_music/__main__.py
sublime_music/app.py
sublime_music/config.py
sublime_music/util.py
sublime_music/adapters/__init__.py
sublime_music/adapters/adapter_base.py
sublime_music/adapters/api_objects.py
sublime_music/adapters/configure_server_form.py
sublime_music/adapters/manager.py
sublime_music/adapters/filesystem/__init__.py
sublime_music/adapters/filesystem/adapter.py
sublime_music/adapters/filesystem/models.py
sublime_music/adapters/filesystem/sqlite_extensions.py
sublime_music/adapters/icons/config-error-symbolic.svg
sublime_music/adapters/icons/config-ok-symbolic.svg
sublime_music/adapters/images/default-album-art.png
sublime_music/adapters/images/default-album-art.svg
sublime_music/adapters/subsonic/__init__.py
sublime_music/adapters/subsonic/adapter.py
sublime_music/adapters/subsonic/api_objects.py
sublime_music/adapters/subsonic/api_specs/subsonic-rest-api-1.1.0.xsd
sublime_music/adapters/subsonic/api_specs/subsonic-rest-api-1.1.1.xsd
sublime_music/adapters/subsonic/api_specs/subsonic-rest-api-1.10.2.xsd
sublime_music/adapters/subsonic/api_specs/subsonic-rest-api-1.11.0.xsd
sublime_music/adapters/subsonic/api_specs/subsonic-rest-api-1.12.0.xsd
sublime_music/adapters/subsonic/api_specs/subsonic-rest-api-1.13.0.xsd
sublime_music/adapters/subsonic/api_specs/subsonic-rest-api-1.14.0.xsd
sublime_music/adapters/subsonic/api_specs/subsonic-rest-api-1.15.0.xsd
sublime_music/adapters/subsonic/api_specs/subsonic-rest-api-1.16.0.xsd
sublime_music/adapters/subsonic/api_specs/subsonic-rest-api-1.16.1.xsd
sublime_music/adapters/subsonic/api_specs/subsonic-rest-api-1.2.0.xsd
sublime_music/adapters/subsonic/api_specs/subsonic-rest-api-1.3.0.xsd
sublime_music/adapters/subsonic/api_specs/subsonic-rest-api-1.4.0.xsd
sublime_music/adapters/subsonic/api_specs/subsonic-rest-api-1.5.0.xsd
sublime_music/adapters/subsonic/api_specs/subsonic-rest-api-1.6.0.xsd
sublime_music/adapters/subsonic/api_specs/subsonic-rest-api-1.7.0.xsd
sublime_music-0.12.0.dist-info/entry_points.txt
sublime_music-0.12.0.dist-info/LICENSE
sublime_music-0.12.0.dist-info/WHEEL
sublime_music-0.12.0.dist-info/METADATA
sublime_music-0.12.0.dist-info/RECORD
