Metadata-Version: 2.1
Name: sublime_music
Version: 0.12.0
Summary: A native GTK *sonic client.
Keywords: airsonic,music,GTK,chromecast,subsonic
Author-email: Sumner Evans <inquiries@sumnerevans.com>
Requires-Python: >=3.10,<4
Classifier: Development Status :: 4 - Beta
Classifier: Environment :: X11 Applications :: GTK
Classifier: Intended Audience :: End Users/Desktop
Classifier: Operating System :: POSIX
Classifier: Topic :: Multimedia :: Sound/Audio :: Players
Classifier: License :: OSI Approved :: GNU General Public License v3 or later (GPLv3+)
Requires-Dist: bleach
Requires-Dist: dataclasses-json
Requires-Dist: deepdiff
Requires-Dist: thefuzz
Requires-Dist: peewee
Requires-Dist: PyGObject
Requires-Dist: python-dateutil
Requires-Dist: Levenshtein
Requires-Dist: python-mpv
Requires-Dist: requests
Requires-Dist: semver
Requires-Dist: black ; extra == "dev"
Requires-Dist: bottle ; extra == "dev"
Requires-Dist: flake8 ; extra == "dev"
Requires-Dist: flake8-annotations ; extra == "dev"
Requires-Dist: flake8-bugbear ; extra == "dev"
Requires-Dist: flake8-comprehensions ; extra == "dev"
Requires-Dist: flake8-pep3101 ; extra == "dev"
Requires-Dist: flake8-print ; extra == "dev"
Requires-Dist: flit ; extra == "dev"
Requires-Dist: isort ; extra == "dev"
Requires-Dist: mypy ; extra == "dev"
Requires-Dist: pip-tools ; extra == "dev"
Requires-Dist: pre-commit ; extra == "dev"
Requires-Dist: pychromecast ; extra == "dev"
Requires-Dist: requirements-parser ; extra == "dev"
Requires-Dist: termcolor ; extra == "dev"
Requires-Dist: thefuzz ; extra == "dev"
Requires-Dist: types-bleach ; extra == "dev"
Requires-Dist: types-peewee ; extra == "dev"
Requires-Dist: types-python-dateutil ; extra == "dev"
Requires-Dist: types-pyyaml ; extra == "dev"
Requires-Dist: types-requests ; extra == "dev"
Requires-Dist: types-tabulate ; extra == "dev"
Requires-Dist: types-termcolor ; extra == "dev"
Requires-Dist: docutils <0.17 ; extra == "doc"
Requires-Dist: rst2html5 ; extra == "doc"
Requires-Dist: sphinx <5 ; extra == "doc"
Requires-Dist: sphinx_rtd_theme ; extra == "doc"
Requires-Dist: keyring ; extra == "keyring"
Requires-Dist: pytest ; extra == "test"
Requires-Dist: pytest-cov ; extra == "test"
Project-URL: Bug Tracker, https://github.com/sublime-music/sublime-music/issues
Project-URL: Documentation, https://docs.sublimemusic.app
Project-URL: Homepage, https://sublimemusic.app
Project-URL: Source Code, https://github.com/sublime-music/sublime-music
Provides-Extra: dev
Provides-Extra: doc
Provides-Extra: keyring
Provides-Extra: test
